model_prefix/__init__.py
model_prefix/models.py
django_model_prefix-1.1.0.dist-info/LICENSE
django_model_prefix-1.1.0.dist-info/METADATA
django_model_prefix-1.1.0.dist-info/WHEEL
django_model_prefix-1.1.0.dist-info/top_level.txt
django_model_prefix-1.1.0.dist-info/RECORD
